clusttraj/__init__.py
clusttraj/__main__.py
clusttraj/classify.py
clusttraj/distmat.py
clusttraj/io.py
clusttraj/main.py
clusttraj/metrics.py
clusttraj/plot.py
clusttraj/utils.py
clusttraj-1.0.0.dist-info/licenses/LICENSE
clusttraj-1.0.0.dist-info/METADATA
clusttraj-1.0.0.dist-info/WHEEL
clusttraj-1.0.0.dist-info/entry_points.txt
clusttraj-1.0.0.dist-info/top_level.txt
clusttraj-1.0.0.dist-info/RECORD
