Metadata-Version: 2.4
Name: clusttraj
Version: 1.0.0
Summary: Performs clustering of molecular dynamics and Monte Carlo trajectories.
Author-email: Henrique Musseli Cezar <henrique.musseli@gmail.com>
License:                     GNU GENERAL PUBLIC LICENSE
Project-URL: Homepage, https://github.com/hmcezar/clusttraj
Project-URL: Bug Tracker, https://github.com/hmcezar/clusttraj/issues
Classifier: Development Status :: 5 - Production/Stable
Classifier: Intended Audience :: Science/Research
Classifier: Programming Language :: Python
Classifier: Programming Language :: Python :: 3 :: Only
Classifier: Programming Language :: Python :: 3.9
Classifier: Programming Language :: Python :: 3.10
Classifier: Programming Language :: Python :: 3.11
Classifier: Programming Language :: Python :: 3.12
Classifier: Environment :: Console
Classifier: License :: OSI Approved :: GNU General Public License v3 (GPLv3)
Classifier: Operating System :: OS Independent
Classifier: Topic :: Scientific/Engineering
Classifier: Topic :: Scientific/Engineering :: Chemistry
Classifier: Topic :: Scientific/Engineering :: Physics
Requires-Python: >=3.9
License-File: LICENSE
Requires-Dist: numpy
Requires-Dist: rmsd>=1.6.3
Requires-Dist: scipy
Requires-Dist: scikit-learn
Requires-Dist: matplotlib
Requires-Dist: openbabel-wheel>=3.0
Provides-Extra: test
Requires-Dist: pytest; extra == "test"
Requires-Dist: pytest-cov[all]; extra == "test"
Provides-Extra: docs
Requires-Dist: sphinx; extra == "docs"
Requires-Dist: sphinx_rtd_theme; extra == "docs"
Provides-Extra: lint
Requires-Dist: black; extra == "lint"
Provides-Extra: qml
Requires-Dist: qmllib; extra == "qml"
Provides-Extra: all
Requires-Dist: clusttraj[docs,lint,qml,test]; extra == "all"
Dynamic: license-file
